openTEPES/__init__.py
openTEPES/openTEPES.mapbox_token
openTEPES/openTEPES.py
openTEPES/openTEPES_InputData.py
openTEPES/openTEPES_Main.py
openTEPES/openTEPES_ModelFormulation.py
openTEPES/openTEPES_OutputResults.py
openTEPES/openTEPES_ProblemSolving.py
openTEPES/openTEPES_gitinfo.py
openTEPES/.idea/.name
openTEPES/.idea/misc.xml
openTEPES/.idea/modules.xml
openTEPES/.idea/openTEPES.iml
openTEPES/.idea/vcs.xml
openTEPES/.idea/workspace.xml
openTEPES/.idea/inspectionProfiles/profiles_settings.xml
openTEPES/9n/oT_Data_Demand_9n.csv
openTEPES/9n/oT_Data_Duration_9n.csv
openTEPES/9n/oT_Data_Emission_9n.csv
openTEPES/9n/oT_Data_EnergyInflows_9n.csv
openTEPES/9n/oT_Data_EnergyOutflows_9n.csv
openTEPES/9n/oT_Data_Generation_9n.csv
openTEPES/9n/oT_Data_Inertia_9n.csv
openTEPES/9n/oT_Data_Network_9n.csv
openTEPES/9n/oT_Data_NodeLocation_9n.csv
openTEPES/9n/oT_Data_OperatingReserveDown_9n.csv
openTEPES/9n/oT_Data_OperatingReserveUp_9n.csv
openTEPES/9n/oT_Data_Option_9n.csv
openTEPES/9n/oT_Data_Parameter_9n.csv
openTEPES/9n/oT_Data_Period_9n.csv
openTEPES/9n/oT_Data_RESEnergy_9n.csv
openTEPES/9n/oT_Data_ReserveMargin_9n.csv
openTEPES/9n/oT_Data_Scenario_9n.csv
openTEPES/9n/oT_Data_Stage_9n.csv
openTEPES/9n/oT_Data_VariableEmissionCost_9n.csv
openTEPES/9n/oT_Data_VariableFuelCost_9n.csv
openTEPES/9n/oT_Data_VariableMaxConsumption_9n.csv
openTEPES/9n/oT_Data_VariableMaxEnergy_9n.csv
openTEPES/9n/oT_Data_VariableMaxGeneration_9n.csv
openTEPES/9n/oT_Data_VariableMaxStorage_9n.csv
openTEPES/9n/oT_Data_VariableMinConsumption_9n.csv
openTEPES/9n/oT_Data_VariableMinEnergy_9n.csv
openTEPES/9n/oT_Data_VariableMinGeneration_9n.csv
openTEPES/9n/oT_Data_VariableMinStorage_9n.csv
openTEPES/9n/oT_Dict_AreaToRegion_9n.csv
openTEPES/9n/oT_Dict_Area_9n.csv
openTEPES/9n/oT_Dict_Circuit_9n.csv
openTEPES/9n/oT_Dict_Generation_9n.csv
openTEPES/9n/oT_Dict_Line_9n.csv
openTEPES/9n/oT_Dict_LoadLevel_9n.csv
openTEPES/9n/oT_Dict_NodeToZone_9n.csv
openTEPES/9n/oT_Dict_Node_9n.csv
opentepes-4.18.6.dist-info/entry_points.txt
opentepes-4.18.6.dist-info/licenses/LICENSE
opentepes-4.18.6.dist-info/WHEEL
opentepes-4.18.6.dist-info/METADATA
opentepes-4.18.6.dist-info/RECORD
