Metadata-Version: 2.4
Name: openTEPES
Version: 4.18.6
Summary: Open Generation, Storage, and Transmission Operation and Expansion Planning Model with RES and ESS (openTEPES)
Home-page: https://opentepes.readthedocs.io/en/latest/index.html
Author: IIT-EnergySystemModels
Author-email: andres.ramos@comillas.edu
Requires-Python: >=3.11
Classifier: Development Status :: 5 - Production/Stable
Classifier: Intended Audience :: Science/Research
Classifier: License :: OSI Approved :: GNU General Public License v3 or later (GPLv3+)
Classifier: Operating System :: OS Independent
Classifier: Programming Language :: Python :: 3.11
License-File: LICENSE
Requires-Dist: pyomo>=5.7.3
Requires-Dist: matplotlib>=3.3.4
Requires-Dist: numpy>=1.20.1
Requires-Dist: pandas>=1.2.3
Requires-Dist: plotly>=5.7.0
Requires-Dist: colour>=0.1.5
Requires-Dist: altair>=5.0.0
Requires-Dist: psutil>=5.8.0
Requires-Dist: jsonschema>=4.16.0
Requires-Dist: networkx>=3.3
Requires-Dist: dill>=0.3.8
